odoo/addons/stock_request_analytic/README.rst
odoo/addons/stock_request_analytic/__init__.py
odoo/addons/stock_request_analytic/__manifest__.py
odoo/addons/stock_request_analytic/i18n/stock_request_analytic.pot
odoo/addons/stock_request_analytic/models/__init__.py
odoo/addons/stock_request_analytic/models/analytic.py
odoo/addons/stock_request_analytic/models/procurement_rule.py
odoo/addons/stock_request_analytic/models/stock_request.py
odoo/addons/stock_request_analytic/models/stock_request_order.py
odoo/addons/stock_request_analytic/security/ir.model.access.csv
odoo/addons/stock_request_analytic/static/description/icon.png
odoo/addons/stock_request_analytic/tests/__init__.py
odoo/addons/stock_request_analytic/tests/test_stock_request_analytic.py
odoo/addons/stock_request_analytic/views/analytic_views.xml
odoo/addons/stock_request_analytic/views/stock_request_order_views.xml
odoo/addons/stock_request_analytic/views/stock_request_views.xml
odoo11_addon_stock_request_analytic-11.0.2.0.3.dist-info/METADATA
odoo11_addon_stock_request_analytic-11.0.2.0.3.dist-info/WHEEL
odoo11_addon_stock_request_analytic-11.0.2.0.3.dist-info/top_level.txt
odoo11_addon_stock_request_analytic-11.0.2.0.3.dist-info/RECORD
